octopuscl/__init__.py
octopuscl/constants.py
octopuscl/env.py
octopuscl/types.py
octopuscl/utils.py
octopuscl/data/__init__.py
octopuscl/data/datasets.py
octopuscl/data/loaders.py
octopuscl/data/processors.py
octopuscl/data/repository.py
octopuscl/data/splitting.py
octopuscl/data/transforms.py
octopuscl/data/utils.py
octopuscl/experiments/__init__.py
octopuscl/experiments/artifacts.py
octopuscl/experiments/aws.py
octopuscl/experiments/base.py
octopuscl/experiments/metrics.py
octopuscl/experiments/orchestrator.py
octopuscl/experiments/utils.py
octopuscl/experiments/delegation/__init__.py
octopuscl/experiments/delegation/avalanche.py
octopuscl/experiments/delegation/base.py
octopuscl/models/__init__.py
octopuscl/models/base.py
octopuscl/models/common/__init__.py
octopuscl/models/common/pytorch.py
octopuscl/models/flava/__init__.py
octopuscl/models/flava/modeling_flava.py
octopuscl/scripts/__init__.py
octopuscl/scripts/run_dataset_manager.py
octopuscl/scripts/run_experiments.py
octopuscl/scripts/run_trial.py
octopuscl/scripts/utils.py
octopuscl_lib-0.1.0b0.dist-info/LICENSE
octopuscl_lib-0.1.0b0.dist-info/METADATA
octopuscl_lib-0.1.0b0.dist-info/WHEEL
octopuscl_lib-0.1.0b0.dist-info/entry_points.txt
octopuscl_lib-0.1.0b0.dist-info/top_level.txt
octopuscl_lib-0.1.0b0.dist-info/RECORD
