Metadata-Version: 2.1
Name: octopuscl-lib
Version: 0.1.0b0
Summary: A framework for building and experimenting with multimodal models in continual learning scenarios
Author-email: Neuraptic AI <contact@neuraptic.ai>
License: MIT
Project-URL: Homepage, https://github.com/neuraptic/octopuscl
Classifier: Programming Language :: Python :: 3.10
Classifier: License :: OSI Approved :: MIT License
Classifier: Operating System :: OS Independent
Requires-Python: >=3.10
License-File: LICENSE
Requires-Dist: avalanche-lib
Requires-Dist: boto3
Requires-Dist: botocore
Requires-Dist: docker
Requires-Dist: marshmallow
Requires-Dist: marshmallow_enum
Requires-Dist: mlflow
Requires-Dist: numpy>=1.20
Requires-Dist: overrides
Requires-Dist: pandas
Requires-Dist: paramiko
Requires-Dist: pyyaml
Requires-Dist: torch
Requires-Dist: tqdm
Requires-Dist: transformers
